pyVisualCrossing/__init__.py
pyVisualCrossing/api.py
pyVisualCrossing/const.py
pyVisualCrossing/data.py
pyVisualCrossing-0.1.16.dist-info/LICENSE
pyVisualCrossing-0.1.16.dist-info/METADATA
pyVisualCrossing-0.1.16.dist-info/WHEEL
pyVisualCrossing-0.1.16.dist-info/top_level.txt
pyVisualCrossing-0.1.16.dist-info/RECORD
