Metadata-Version: 2.1
Name: pyVisualCrossing
Version: 0.1.16
Summary: Gets the weather data from Visual Crossing
Home-page: https://github.com/briis/pyVisualCrossing
Author: briis
Author-email: bjarne@briis.com
License: MIT
Classifier: Programming Language :: Python :: 3
Classifier: License :: OSI Approved :: MIT License
Classifier: Operating System :: OS Independent
Classifier: Development Status :: 4 - Beta
License-File: LICENSE
